// class version 52.0 (52)
// access flags 0x21
public class bytecode/BasicGrammer {

  // compiled from: BasicGrammer.java

  // access flags 0x1
  public <init>()V
   L0
    LINENUMBER 5 L0
    ALOAD 0
    INVOKESPECIAL java/lang/Object.<init> ()V
    RETURN
   L1
    LOCALVARIABLE this Lbytecode/BasicGrammer; L0 L1 0
    MAXSTACK = 1
    MAXLOCALS = 1

  // access flags 0x9
  public static main([Ljava/lang/String;)V
   L0
    LINENUMBER 8 L0
    NEW bytecode/BasicGrammer
    DUP
    INVOKESPECIAL bytecode/BasicGrammer.<init> ()V
    ASTORE 1
   L1
    LINENUMBER 9 L1
    ALOAD 1
    BIPUSH 10
    ICONST_5
    INVOKEVIRTUAL bytecode/BasicGrammer.test (II)V
   L2
    LINENUMBER 10 L2
    RETURN
   L3
    LOCALVARIABLE args [Ljava/lang/String; L0 L3 0
    LOCALVARIABLE bg Lbytecode/BasicGrammer; L1 L3 1
    MAXSTACK = 3
    MAXLOCALS = 2

  // access flags 0x1
  public test(II)V
   L0
    LINENUMBER 13 L0
    ILOAD 1
    ILOAD 2
    IADD
    ISTORE 3
   L1
    LINENUMBER 14 L1
    ILOAD 3
    NEWARRAY T_INT
    ASTORE 4
   L2
    LINENUMBER 15 L2
    ICONST_0
    ISTORE 5
   L3
   FRAME APPEND [I [I I]
    ILOAD 5
    ALOAD 4
    ARRAYLENGTH
    IF_ICMPGE L4
   L5
    LINENUMBER 16 L5
    ALOAD 4
    ILOAD 5
    DUP2
    IALOAD
    ICONST_1
    IADD
    IASTORE
   L6
    LINENUMBER 15 L6
    IINC 5 1
    GOTO L3
   L4
    LINENUMBER 18 L4
   FRAME CHOP 1
    GETSTATIC java/lang/System.out : Ljava/io/PrintStream;
    ALOAD 4
    INVOKESTATIC java/util/Arrays.toString ([I)Ljava/lang/String;
    INVOKEVIRTUAL java/io/PrintStream.println (Ljava/lang/String;)V
   L7
    LINENUMBER 19 L7
    RETURN
   L8
    LOCALVARIABLE i I L3 L4 5
    LOCALVARIABLE this Lbytecode/BasicGrammer; L0 L8 0
    LOCALVARIABLE a I L0 L8 1
    LOCALVARIABLE b I L0 L8 2
    LOCALVARIABLE c I L1 L8 3
    LOCALVARIABLE array [I L2 L8 4
    MAXSTACK = 4
    MAXLOCALS = 6
}
